DataCraftHub/__init__.py
DataCraftHub/main.py
DataCraftHub-0.1.dist-info/METADATA
DataCraftHub-0.1.dist-info/WHEEL
DataCraftHub-0.1.dist-info/entry_points.txt
DataCraftHub-0.1.dist-info/top_level.txt
DataCraftHub-0.1.dist-info/RECORD
