Metadata-Version: 2.1
Name: DataCraftHub
Version: 0.1
